svd_downloader/__main__.py
svd_downloader/downloader.py
svd_downloader-0.1.1.dist-info/LICENSE
svd_downloader-0.1.1.dist-info/METADATA
svd_downloader-0.1.1.dist-info/WHEEL
svd_downloader-0.1.1.dist-info/top_level.txt
svd_downloader-0.1.1.dist-info/RECORD
