Metadata-Version: 2.1
Name: svd-downloader
Version: 0.1.1
Summary: Simple utility to download Saarbruecken Voice Database
Home-page: https://github.com/rijulg/svd-downloader
Author: Rijul Gupta
Author-email: rijulg@neblar.com
License: MIT
Keywords: Downloader,SVD,Disordered Voice Database
Classifier: Development Status :: 4 - Beta
Classifier: Intended Audience :: Developers
Classifier: License :: OSI Approved :: MIT License
Classifier: Operating System :: OS Independent
Classifier: Topic :: Utilities
License-File: LICENSE
Requires-Dist: dask >=2024.1.1
Requires-Dist: beautifulsoup4 >=4.12.3
Requires-Dist: requests >=2.31.0
